bmcs_shear/__init__.py
bmcs_shear/api.py
bmcs_shear/version.py
bmcs_shear/beam_design/__init__.py
bmcs_shear/beam_design/beam_design.py
bmcs_shear/beam_design/beam_design_original.py
bmcs_shear/dic_crack/__init__.py
bmcs_shear/dic_crack/dic_aligned_grid.py
bmcs_shear/dic_crack/dic_crack.py
bmcs_shear/dic_crack/dic_crack_cor.py
bmcs_shear/dic_crack/dic_crack_list.py
bmcs_shear/dic_crack/dic_grid.py
bmcs_shear/dic_crack/dic_inp_grid.py
bmcs_shear/dic_crack/dic_inp_unstructured_points.py
bmcs_shear/dic_crack/dic_state_fields.py
bmcs_shear/dic_crack/dic_stress_profile.py
bmcs_shear/dic_crack/dic_test_crack.py
bmcs_shear/dic_crack/i_dic_crack.py
bmcs_shear/dic_crack/i_dic_inp.py
bmcs_shear/matmod/__init__.py
bmcs_shear/matmod/i_matmod.py
bmcs_shear/matmod/sz_concrete/__init__.py
bmcs_shear/matmod/sz_concrete/sz_advanced/__init__.py
bmcs_shear/matmod/sz_concrete/sz_advanced/sz_advanced.py
bmcs_shear/matmod/sz_concrete/sz_advanced/sz_advanced_ver2.py
bmcs_shear/matmod/sz_concrete/sz_advanced/sz_aggregate_interlock.py
bmcs_shear/matmod/sz_concrete/sz_advanced/sz_compressive_hardening.py
bmcs_shear/matmod/sz_concrete/sz_advanced/sz_softening_tensile_behavior.py
bmcs_shear/matmod/sz_concrete/sz_simple/__init__.py
bmcs_shear/matmod/sz_concrete/sz_simple/sz_concrete.py
bmcs_shear/matmod/sz_crack_bridge/__init__.py
bmcs_shear/matmod/sz_crack_bridge/cb_advanced/__init__.py
bmcs_shear/matmod/sz_crack_bridge/cb_advanced/sz_crack_bridge_adv.py
bmcs_shear/matmod/sz_crack_bridge/cb_advanced/sz_dowel_action.py
bmcs_shear/matmod/sz_crack_bridge/cb_advanced/sz_pull_out_fib.py
bmcs_shear/matmod/sz_crack_bridge/cb_simple/__init__.py
bmcs_shear/matmod/sz_crack_bridge/cb_simple/sz_crack_bridge.py
bmcs_shear/shear_crack/__init__.py
bmcs_shear/shear_crack/crack_extension.py
bmcs_shear/shear_crack/crack_extension_bending.py
bmcs_shear/shear_crack/crack_path.py
bmcs_shear/shear_crack/crack_propagation.py
bmcs_shear/shear_crack/crack_propagation_hist.py
bmcs_shear-0.0.3a0.dist-info/METADATA
bmcs_shear-0.0.3a0.dist-info/WHEEL
bmcs_shear-0.0.3a0.dist-info/top_level.txt
bmcs_shear-0.0.3a0.dist-info/RECORD
